{
  "type": "script",
  "seleniumVersion": "2",
  "formatVersion": 2,
  "steps": [
    {
      "type": "get",
      "url": "https://www.critizen.com/"
    },
    {
      "type": "clickElement",
      "locator": {
        "type": "xpath",
        "value": "//article[@class='m-home']/div[2]"
      }
    },
    {
      "type": "clickElement",
      "locator": {
        "type": "link text",
        "value": "Ver críticas"
      }
    },
    {
      "type": "clickElement",
      "locator": {
        "type": "xpath",
        "value": "//div[@id='grid-layout']/div[3]/article[2]/div/div/div/a/p"
      }
    }
  ],
  "data": {
    "configs": {},
    "source": "none"
  },
  "inputs": [],
  "timeoutSeconds": 60
}